{"ruT1/bDKUN5iw2+PV+FPbw==":"british-museum-22-640x425.jpg","4Hpq3lvz/o1/OuuUq9SI+Q==":"british_museum_great_court,_london,_uk_-_diliff-2000x1963.jpg","zKm10wn/SGuPypaZHsVvlw==":"55-4-640x469.jpg","3FpJgUkxXc8og5iFHwEbOg==":"british_museum_great_court,_london,_uk_-_diliff-1-2000x1963.jpg","RUzZKkxSOvwjQkKLarFqew==":"unknown-122x70.png","2A/yfo4SgHULEGvegSQccw==":"images-200x200.png","3PeMMZD/KX6qHABWHcnzdg==":"screen%20shot%202019-03-16%20at%202.35.30%20pm-1211x614.png","3PUephQivkevdh7Dg7W7Ew==":"screen%20shot%202019-03-16%20at%202.38.11%20pm-1241x616.png","tJT3mbR2M6oUTvV5wNUHCw==":"screen%20shot%202019-03-16%20at%202.38.34%20pm-1240x617.png","qi4oKu7cSnTZ8X+wOxrmtw==":"screen%20shot%202019-03-16%20at%202.48.45%20pm-1141x596.png","LkRiB/o8bzXEidizQvz+1g==":"screen%20shot%202019-03-16%20at%202.49.25%20pm-1094x617.png","ojA3zv56tTHG7R8yUuyszw==":"screen%20shot%202019-04-06%20at%204.06.32%20pm-1026x768.png","smqKwb9l51udQaKLbSBHqg==":"screen%20shot%202019-04-06%20at%204.06.45%20pm-1025x768.png","cryAHn9+qf8+zOu/xui2QA==":"screen%20shot%202019-04-06%20at%204.07.34%20pm-1022x768.png","zMJmfmiu5XgCXRM2ZiwalQ==":"screen%20shot%202019-04-08%20at%2011.20.03%20am-1023x768.png"}